telemem/__init__.py
telemem/configs.py
telemem/main.py
telemem/utils.py
telemem/mm_utils/__init__.py
telemem/mm_utils/build_database.py
telemem/mm_utils/core.py
telemem/mm_utils/frame_caption.py
telemem/mm_utils/func_call_shema.py
telemem/mm_utils/memory_utils.py
telemem/mm_utils/video_utils.py
telemem-1.1.0.dist-info/METADATA
telemem-1.1.0.dist-info/WHEEL
telemem-1.1.0.dist-info/top_level.txt
telemem-1.1.0.dist-info/RECORD
