Metadata-Version: 2.4
Name: telemem
Version: 1.1.0
Summary: High-performance drop-in replacement of Mem0
License: Apache-2.0
Project-URL: Homepage, https://github.com/TeleAI-UAGI/telemem
Requires-Python: >=3.10
Requires-Dist: openai
Requires-Dist: pydantic
Requires-Dist: chromadb
Requires-Dist: opencv-python-headless
Requires-Dist: nano-vectordb
Requires-Dist: mem0ai
Requires-Dist: tqdm
Requires-Dist: azure-identity
Requires-Dist: yt_dlp
Requires-Dist: faiss-cpu
